gandyns/__init__.py
gandyns/gandyns.py
gandyns-1.0.1.dist-info/METADATA
gandyns-1.0.1.dist-info/RECORD
gandyns-1.0.1.dist-info/WHEEL
gandyns-1.0.1.dist-info/entry_points.txt
gandyns-1.0.1.dist-info/top_level.txt
