Metadata-Version: 2.1
Name: gandyns
Version: 1.0.1
Summary: Update gandi DNS record with current public IP
Home-page: https://github.com/r0x73/gandyns.git
Author: Raphaël Santos
Author-email: r@0x73.ch
License: UNKNOWN
Keywords: dns gandi api
Platform: UNKNOWN
Classifier: Environment :: Console
Classifier: Development Status :: 5 - Production/Stable
Classifier: Intended Audience :: Developers
Classifier: Intended Audience :: System Administrators
Classifier: Intended Audience :: End Users/Desktop
Classifier: Topic :: Internet :: Name Service (DNS)
Classifier: License :: OSI Approved :: MIT License
Classifier: Programming Language :: Python :: 3.6
Requires-Dist: requests (>=2.18.4)
